scrapydd/__init__.py
scrapydd/agent.py
scrapydd/client.py
scrapydd/cluster.py
scrapydd/config.py
scrapydd/daemonize.py
scrapydd/eggstorage.py
scrapydd/exceptions.py
scrapydd/executor.py
scrapydd/filelock.py
scrapydd/mail.py
scrapydd/main.py
scrapydd/models.py
scrapydd/nodes.py
scrapydd/process.py
scrapydd/project.py
scrapydd/schedule.py
scrapydd/scheduleutil.py
scrapydd/scrapydd.default.conf
scrapydd/security.py
scrapydd/settting.py
scrapydd/spiderplugin.py
scrapydd/ssl_gen.py
scrapydd/storage.py
scrapydd/stream.py
scrapydd/webhook.py
scrapydd/workspace.py
scrapydd/commands/__init__.py
scrapydd/commands/backup.py
scrapydd/commands/package.py
scrapydd/commands/resetpassword.py
scrapydd/commands/restore.py
scrapydd/commands/run.py
scrapydd/grpcserver/__init__.py
scrapydd/grpcserver/grpc_asyncio.py
scrapydd/grpcserver/server.py
scrapydd/grpcserver/service_pb2.py
scrapydd/grpcserver/service_pb2_grpc.py
scrapydd/grpcservice/__init__.py
scrapydd/grpcservice/generic_client_interceptor.py
scrapydd/grpcservice/grpc_asyncio.py
scrapydd/grpcservice/server.py
scrapydd/grpcservice/service_pb2.py
scrapydd/grpcservice/service_pb2_grpc.py
scrapydd/handlers/__init__.py
scrapydd/handlers/admin.py
scrapydd/handlers/api.py
scrapydd/handlers/auth.py
scrapydd/handlers/base.py
scrapydd/handlers/node.py
scrapydd/handlers/profile.py
scrapydd/handlers/rest.py
scrapydd/handlers/webui.py
scrapydd/migrates/__init__.py
scrapydd/migrates/manage.py
scrapydd/migrates/migrate.cfg
scrapydd/migrates/versions/001_create_tables.py
scrapydd/migrates/versions/002_nodes_add_is_alive.py
scrapydd/migrates/versions/003_queue_add_pid.py
scrapydd/migrates/versions/004_historical_jobs.py
scrapydd/migrates/versions/005_create_webhook_jobs.py
scrapydd/migrates/versions/006_items_count.py
scrapydd/migrates/versions/007_spider_concurrency.py
scrapydd/migrates/versions/008_job_status_foreignkey.py
scrapydd/migrates/versions/009_move_webhook_setting_to_spider_settings.py
scrapydd-0.7.5.dist-info/LICENSE
scrapydd-0.7.5.dist-info/METADATA
scrapydd-0.7.5.dist-info/WHEEL
scrapydd-0.7.5.dist-info/entry_points.txt
scrapydd-0.7.5.dist-info/top_level.txt
scrapydd-0.7.5.dist-info/RECORD
