Metadata-Version: 2.1
Name: scrapydd
Version: 0.7.5
Summary: distributed scrapy spider scheduling system
Home-page: http://github.com/kevenli/scrapydd
Author: kevenli
Author-email: pbleester@gmail.com
License: UNKNOWN
Platform: UNKNOWN
Requires-Dist: apscheduler (==3.6.3)
Requires-Dist: Automat (==0.8.0)
Requires-Dist: chardet (==3.0.4)
Requires-Dist: docker (==4.2.2)
Requires-Dist: requests (==2.20.0)
Requires-Dist: pysyncobj (>=0.2.3)
Requires-Dist: subprocess32 (==3.5.4)
Requires-Dist: scrapy (<3.0,>=2.0)
Requires-Dist: service-identity (==18.1.0)
Requires-Dist: six (==1.15.0)
Requires-Dist: sqlalchemy (==1.3.18)
Requires-Dist: sqlalchemy-migrate (==0.13.0)
Requires-Dist: sqlalchemy-utils
Requires-Dist: tornado (==6.0.4)
Requires-Dist: virtualenv (>=20.0)
Requires-Dist: w3lib (==1.22.0)
Requires-Dist: pyaml (==20.4.0)
Requires-Dist: pymysql (==0.10.0)
Requires-Dist: namegenerator (==1.0.6)
Requires-Dist: grpcio (==1.31.0)
Requires-Dist: grpcio-tools (==1.31.0)
